main/simple_processor32bits.v
`timescale 1ns/1ns

//Instruction memory
module InstructionMemory (clk, address, instruction);
input		clk;
input	[63:0]	address;
output	[31:0]	instruction;
reg	[31:0]	instruction;
reg	[7:0]	memAddr;
reg	[31:0]	Imem[0:0];
initial	
	$readmemb ("Instruction.txt", Imem);
always @(posedge clk) begin
	memAddr = address;
	instruction = Imem[memAddr];
end
endmodule

//PROGRAM COUNTER
module Programcounter (clk, reset, cont,add);

input		clk;//Señales de reloj
input		reset;//reset de reloj
input [63:0] add;
output	[63:0]	cont;//contador

// Las salidas se definen como registros también                                              
reg	[63:0]	cont;
always @ (posedge clk)
begin
  if (reset)
    cont <= 16'h0;
  else if (add)
    cont <= cont + add; 
  else 
    cont <= cont + 1'b1;
end
endmodule
//REGISTER MEMORY
`timescale 1ns / 1ps
module RegisterMemory(rs1,rs2,rd,WriteData,RegWrite,Data1,Data2,clk);
input    clk;      
input    RegWrite; 
input  [4:0] rs1;        
input  [4:0] rs2;        
input  [4:0] rd;     
input  [63:0] WriteData; 
output  [63:0] Data1;    
output  [63:0] Data2;    
reg [63:0] RF [63:0];

assign Data1 = {59'b00000000000000000000000000000000000000000000000000000000000,rs1};                         //64'b0000000000000000000000000000000000000000000000000000000000000010;//RF[rs1];
assign Data2 = {59'b00000000000000000000000000000000000000000000000000000000000,rs2};//RF[rs2];
always @ (posedge clk ) begin
  if(RegWrite) begin
    RF[rd] <= WriteData;
  end
end
endmodule

//MULTIPLEXOR REGISTER
module multiplexor_bh (i0,i1,select,y);
  input [63:0] i0;
  input [63:0] i1;
  input select;
  output [63:0]y;
  reg y;
  
  always @ (i0 or i1)
    case (select)
      1'b0: y = i0;
      1'b1: y = i1;
    endcase
endmodule

//ALU
module ALU(A,B,ALUcontrol,ALUresult,Zero);

 input  [63:0] A;  
 input  [63:0] B; 
 input  [3:0] ALUcontrol; 
 output reg [63:0] ALUresult;
 output Zero;
assign Zero = (ALUresult == 0); 
always @(ALUcontrol,A,B)

  case(ALUcontrol)
    4'b0010:  ALUresult = A + B; //add  //ld sd
    4'b0110:  ALUresult = A - B; //sub  //beq
    4'b0000:  ALUresult = A & B; //and
    4'b0001:  ALUresult = A | B; //or
    default : ALUresult <= 0;// por defecto A= 0, no debería suceder;
  endcase
endmodule
//CONTROL UNIT
module control_unit(
                    input [6:0] opcode,
                    output reg[1:0] alu_op,
                    output reg branch,memRead,memToReg,memWrite,aluSrc,regWrite
    );
    always @(*)
    begin
        case(opcode)
        7'b0110011: //ADD
        begin 
            alu_op =   2'b10;
            branch =   1'b0;
            memRead =  1'b0;
            memToReg = 1'b0;
            memWrite = 1'b0;
            aluSrc =   1'b0;
            regWrite = 1'b1;
        end
        7'b0110011: //SUBSTRACT
        begin
            alu_op =   2'b10;
            branch =   1'b0;
            memRead =  1'b0;
            memToReg = 1'b0;
            memWrite = 1'b0;
            aluSrc =   1'b0;
            regWrite = 1'b1;
        end
        7'b0110011: //AND
        begin
        alu_op =   2'b10;
        branch =   1'b0;
        memRead =  1'b0;
        memToReg = 1'b0;
        memWrite = 1'b0;
        aluSrc =   1'b0;
        regWrite = 1'b1;

        end
        7'b0110011: //OR
        begin
        alu_op =   2'b10;
        branch =   1'b0;
        memRead =  1'b0;
        memToReg = 1'b0;
        memWrite = 1'b0;
        aluSrc =   1'b0;
        regWrite = 1'b1;
        end
        //////////////////////
        7'b0000011: //LD
        begin
        alu_op =   2'b00;
        branch =   1'b0;
        memRead =  1'b1;
        memToReg = 1'b1;
        memWrite = 1'b0;
        aluSrc =   1'b1;
        regWrite = 1'b1;
        end
        7'b0100011: //SD
        begin
        alu_op =   2'b00;
        branch =   1'b0;
        memRead =  1'b0;
        memWrite = 1'b1;
        aluSrc =   1'b1;
        regWrite = 1'b0;
        memToReg = 1'bx;


        end
        7'b1100011: //BEQ
        begin
        alu_op =   2'b01;
        branch =   1'b1;
        memRead =  1'b0;
        memWrite = 1'b0;
        aluSrc =   1'b0;
        regWrite = 1'b0;
        memToReg = 1'bx;
        end
   endcase 
   end
endmodule

//ALU CONTROL
module ALUcontrol(ALUop,FuncCode,FuncCodeSeven,ALU_Cnt);

input [1:0] ALUop;
input [2:0] FuncCode; ///FUNCT3 3 BITS [14-12]
input FuncCodeSeven; //FUCT 7 POS 30
output reg[3:0] ALU_Cnt;
input wire [5:0] ALUControlIn;

assign ALUControlIn = {ALUop,FuncCode,FuncCodeSeven};
 always @(ALUControlIn)
    casex (ALUControlIn)
        6'b100000: ALU_Cnt=4'b0010;  //add
        6'b100001: ALU_Cnt=4'b0110;  //sub
        6'b101110: ALU_Cnt=4'b0000;  //and
        6'b101100: ALU_Cnt=4'b0001;  //or
        6'b00011x: ALU_Cnt=4'b0010;  //ld
        6'b10011x: ALU_Cnt=4'b0010;  //sd
        6'b01000x: ALU_Cnt=4'b0110;  //beq
        default: ALU_Cnt=4'b0000;
    endcase
endmodule

//AND Gate
module andGate(
    input D,
    input E,
    output out);

assign out= D & E;
endmodule

//MULTIPLEXOR SHIFT LEFT
module multiplexorShiftLeft(i0,i1,select,y);
  input [63:0] i0;
  input [63:0] i1;
  input select;
  output [63:0]y;
  reg y;
  
  always @ (i0 or i1)
    case (select)
      1'b0: y = i0;
      1'b1: y = i1;
    endcase
endmodule

//ADD + FOUR
module addFour(cont,salidaAddFour);
input clk;
input [63:0] cont;
output reg [63:0]salidaAddFour;

always @(posedge clk)
        salidaAddFour = salidaAddFour  + 4;
endmodule

//ADD <<
module addLeft (clk,contProgramData,shiftLef,salidaAddLeft);
input clk;
input [63:0] contProgramData;
input [63:0] shiftLef;
output [63:0] salidaAddLeft;
reg  [63:0] salidaAddLeft;
parameter B= 1;

always @(posedge clk)
    salidaAddLeft = shiftLef << B  + contProgramData;
endmodule

//IMMGEN
module  Imm_Gen(instruction_imm, clk,wireConection);
  input [31:0] instruction_imm;
  input clk; 
  wire [11:0] Data_1;
  wire Data_2;
  output reg [63:0] wireConection;
  reg One = 52'b1111111111111111111111111111111111111111111111111111;
  reg Cero = 52'b0000000000000000000000000000000000000000000000000000;
  assign Data_1 = instruction_imm[31:20];
  assign Data_2 = instruction_imm[31:31];

always @ (posedge clk) 
   if(Data_2 == 1)
    wireConection = {One, Data_1};
   else 
    wireConection = {Cero, Data_2};
  
endmodule

//DATA MEMORY
module data_memory (
input wire [63:0] Adress,          // Memory Address
input wire [63:0] WriteData,    // Memory Address Contents
input wire MemWrite, MemRead,
input wire clk,                  // All synchronous elements, including memories, should have a clock signal
output reg [63:0] ReadData      // Output of Memory Address Contents
);

reg [63:0] MEMO[0:1024];  // 256 words of 32-bit memory

time i;

initial begin
  ReadData <= 0;
  for (i = 0; i < 1023; i = i + 1) begin
    MEMO[i] = i;
  end
end

// Using @(Adress) will lead to unexpected behavior as memories are synchronous elements like registers
always @(posedge clk) begin
  if (MemWrite == 1'b1) begin
    MEMO[Adress] <= WriteData;
  end
  // Use MemRead to indicate a valid address is on the line and read the memory into a register at that address when MemRead is asserted
  if (MemRead == 1'b1) begin
    ReadData <= MEMO[Adress];
  end
end
endmodule

//MULTIPLEXOR DATAMEMORY
module multiplexorDataMemory(i3,i4,selectMemory,outMulti);
  input [63:0] i3;
  input [63:0] i4;
  input selectMemory;
  output [63:0] outMulti;
  reg outMulti;
  
  always @ (i3 or i4)
    case (selectMemory)
      1'b0: outMulti = i3;
      1'b1: outMulti = i4;
    endcase
endmodule




//SIMPLE PROCCESOR OF 32 BITS
module simple_processor ( 
    input clk,reset
    );
    // output salidaAddFour
    
wire [63:0] conexion1; //PROGRAM COUNTER TO INSTRUCTIONMEMORY,ADDFOUR,ADDLEFT
wire [31:0] conexion2; //INSTRUCTION MEMORY TO REGISTERMEMORY(RS1,RS2,RD),ALUCONTROL(funcode,funcondeseven)
wire [63:0] conexion3; //REGISTER MEMORY TO MULTIPLEXOR
wire [63:0] conexion4; //REGISTER MEMORU TO ALU A
wire [63:0] conexion5; // MULTIPLEXOR TO ALU B
wire conexion6;         // REGISTER MEMORY TO CONTROL UNIT WITH (REGWRITE)
wire [1:0] conexion7; // CONTROL UNIT WITH ALUOP TO ALUCONTROL
wire [3:0] conexion8; // ALU CONTROL to ALU
wire conexion9; //ALUSRC to  MULTIPLEXOR
wire conexion10; //branch to AND
wire conexion11; //zero to AND
wire [63:0] conexion12; //ADDFOUR TO MULTIPLEXOR
wire conexion13; //AND to multiplexor
wire [63:0] conexion14; //OUTPUT IMM TO MULTIPLEXOR AND ADDSHIFTLEFT
wire [63:0] conexion15; //ADDSUMLEFT TO MULTIPLEXOR 01
wire [63:0] conexion16; //ALU RESULT TO ADDRES OR MULTIPLEXOR DATAMEMORY
wire conexion17; // CONTROL MEMWRITE TO DATA MEMORY MEMWRITE
wire conexion18; // CONTROL MEMREAD TO DATA MEMORY MEMREAD
wire conexion19; //CONTROL MEMTOREG TO MULTIPLEXORDATAMEMORY
wire [63:0] conexion20; //DATA MEMORY READ DATA TO MULTIDATAMEMORY
wire [63:0] conexion21; //MULTIPLEXOR DATA MEMORY TO REGISTER MEMORY WRITEDATA
wire [63:0] conexion22; //MULTIPLEXOR SHIFTLEFT TO PC

//Union Modulos//
InstructionMemory im_instance(
    .clk(clk), 
    .address(conexion1),
    .instruction(conexion2)
    );

Programcounter pc_instance(
    .clk(clk), 
    .reset(reset), 
    .cont(conexion1),
    .add(conexion22)
    );

RegisterMemory RegisterMemory_instance(
    .rs1(conexion2[19:15]),
    .rs2(conexion2[24:20]),
    .rd(conexion2[11:7]),
    .WriteData(conexion21),
    .RegWrite(conexion6),
    .Data1(conexion4),
    .Data2(conexion3),
    .clk(clk));

multiplexor_bh multiplexor_bh_intance(
    .i0(conexion3),
    .i1(conexion14), 
    .select(conexion9),
    .y(conexion5));

ALU alu_instance(
    .A(conexion4),
    .B(conexion5),
    .ALUcontrol(conexion8),
    .ALUresult(conexion16),
    .Zero(conexion11));

control_unit control_unit_instance(
    .opcode(conexion2[6:0]),
    .alu_op(conexion7),
    .branch(conexion10),
    .memRead(conexion18),
    .memToReg(conexion19),
    .memWrite(conexion17),
    .aluSrc(conexion9),
    .regWrite(conexion6)
    );

ALUcontrol ALUcontrol_instance(
    .ALUop(conexion7),
    .FuncCode(conexion2[14:12]),
    .FuncCodeSeven(conexion2[30:30]),
    .ALU_Cnt(conexion8)
    );

andGate andGate_instance(
    .D(conexion10),
    .E(conexion11),
    .out(conexion13)); 

multiplexorShiftLeft multiplexorShiftLeft_instance(
    .i0(conexion12),
    .i1(conexion15), 
    .select(conexion13),
    .y(conexion22)
    );   

addFour addFour_instance(
    .cont(conexion1),
    .salidaAddFour(conexion12)
    );

addLeft addLeft_instance(
    .clk(clk),
    .contProgramData(conexion1),
    .shiftLef(conexion14), 
    .salidaAddLeft(conexion15)
    );


Imm_Gen Imm_Gen_instance(
    .instruction_imm(conexion2), 
    .wireConection(conexion14), 
    .clk(clk)
    );

data_memory data_memory_instance(
    .Adress(conexion16),         
    .WriteData(conexion3),    
    .MemWrite(conexion17), 
    .MemRead(conexion18),
    .clk(clk),                  
    .ReadData(conexion20)      
);

multiplexorDataMemory multiplexorDataMemory_instance(
    .i3(conexion16),//0 
    .i4(conexion20),  //1
    .selectMemory(conexion19),
    .outMulti(conexion21)
    );
endmodule

main/simple_proccessor32bits_tb.v
`include "simple_processor32bits.v"
`timescale 1ns/1ns

module simple_proccessor32bits_tb;
reg clk = 0;
reg reset;

simple_processor simple_proccessor32bitstb(clk, reset);

initial begin

	$dumpfile("simple_proccessor32bits_tb.vcd");
	$dumpvars;
    reset = 0;
	#70
	reset = 1;
	#70
	reset = 0;
	#70
	reset = 1;
    #70
    reset = 0;
	#70
	reset = 1;
	#70
	reset = 0;
	#70
	reset = 1;
    
	$finish(500);
	
end

always begin

#10 clk = ~clk;

end

endmodule

main/simple_proccessor32bits_tb.vcd
$date
	Thu Dec 10 22:22:57 2020
$end
$version
	Icarus Verilog
$end
$timescale
	1ps
$end
$scope module simple_proccessor32bits_tb $end
$var reg 1 ! clk $end
$var reg 1 " reset $end
$scope module simple_proccessor32bitstb $end
$var wire 1 ! clk $end
$var wire 1 " reset $end
$var wire 1 # conexion9 $end
$var wire 4 $ conexion8 [3:0] $end
$var wire 2 % conexion7 [1:0] $end
$var wire 1 & conexion6 $end
$var wire 64 ' conexion5 [63:0] $end
$var wire 64 ( conexion4 [63:0] $end
$var wire 64 ) conexion3 [63:0] $end
$var wire 64 * conexion22 [63:0] $end
$var wire 64 + conexion21 [63:0] $end
$var wire 64 , conexion20 [63:0] $end
$var wire 32 - conexion2 [31:0] $end
$var wire 1 . conexion19 $end
$var wire 1 / conexion18 $end
$var wire 1 0 conexion17 $end
$var wire 64 1 conexion16 [63:0] $end
$var wire 64 2 conexion15 [63:0] $end
$var wire 64 3 conexion14 [63:0] $end
$var wire 1 4 conexion13 $end
$var wire 64 5 conexion12 [63:0] $end
$var wire 1 6 conexion11 $end
$var wire 1 7 conexion10 $end
$var wire 64 8 conexion1 [63:0] $end
$scope module ALUcontrol_instance $end
$var wire 3 9 FuncCode [2:0] $end
$var wire 1 : FuncCodeSeven $end
$var wire 2 ; ALUop [1:0] $end
$var wire 6 < ALUControlIn [5:0] $end
$var reg 4 = ALU_Cnt [3:0] $end
$upscope $end
$scope module Imm_Gen_instance $end
$var wire 1 ! clk $end
$var wire 32 > instruction_imm [31:0] $end
$var wire 1 ? Data_2 $end
$var wire 12 @ Data_1 [11:0] $end
$var reg 1 A Cero $end
$var reg 1 B One $end
$var reg 64 C wireConection [63:0] $end
$upscope $end
$scope module RegisterMemory_instance $end
$var wire 1 ! clk $end
$var wire 5 D rd [4:0] $end
$var wire 5 E rs1 [4:0] $end
$var wire 5 F rs2 [4:0] $end
$var wire 64 G WriteData [63:0] $end
$var wire 1 & RegWrite $end
$var wire 64 H Data2 [63:0] $end
$var wire 64 I Data1 [63:0] $end
$upscope $end
$scope module addFour_instance $end
$var wire 1 J clk $end
$var wire 64 K cont [63:0] $end
$var reg 64 L salidaAddFour [63:0] $end
$upscope $end
$scope module addLeft_instance $end
$var wire 1 ! clk $end
$var wire 64 M shiftLef [63:0] $end
$var wire 64 N contProgramData [63:0] $end
$var reg 64 O salidaAddLeft [63:0] $end
$upscope $end
$scope module alu_instance $end
$var wire 64 P A [63:0] $end
$var wire 4 Q ALUcontrol [3:0] $end
$var wire 1 6 Zero $end
$var wire 64 R B [63:0] $end
$var reg 64 S ALUresult [63:0] $end
$upscope $end
$scope module andGate_instance $end
$var wire 1 6 E $end
$var wire 1 4 out $end
$var wire 1 7 D $end
$upscope $end
$scope module control_unit_instance $end
$var wire 7 T opcode [6:0] $end
$var reg 1 # aluSrc $end
$var reg 2 U alu_op [1:0] $end
$var reg 1 7 branch $end
$var reg 1 / memRead $end
$var reg 1 . memToReg $end
$var reg 1 0 memWrite $end
$var reg 1 & regWrite $end
$upscope $end
$scope module data_memory_instance $end
$var wire 64 V Adress [63:0] $end
$var wire 1 / MemRead $end
$var wire 1 0 MemWrite $end
$var wire 64 W WriteData [63:0] $end
$var wire 1 ! clk $end
$var reg 64 X ReadData [63:0] $end
$var reg 64 Y i [63:0] $end
$upscope $end
$scope module im_instance $end
$var wire 1 ! clk $end
$var wire 64 Z address [63:0] $end
$var reg 32 [ instruction [31:0] $end
$var reg 8 \ memAddr [7:0] $end
$upscope $end
$scope module multiplexorDataMemory_instance $end
$var wire 64 ] i3 [63:0] $end
$var wire 64 ^ i4 [63:0] $end
$var wire 1 . selectMemory $end
$var reg 64 _ outMulti [63:0] $end
$upscope $end
$scope module multiplexorShiftLeft_instance $end
$var wire 64 ` i0 [63:0] $end
$var wire 64 a i1 [63:0] $end
$var wire 1 4 select $end
$var reg 64 b y [63:0] $end
$upscope $end
$scope module multiplexor_bh_intance $end
$var wire 64 c i0 [63:0] $end
$var wire 64 d i1 [63:0] $end
$var wire 1 # select $end
$var reg 64 e y [63:0] $end
$upscope $end
$scope module pc_instance $end
$var wire 64 f add [63:0] $end
$var wire 1 ! clk $end
$var wire 1 " reset $end
$var reg 64 g cont [63:0] $end
$upscope $end
$upscope $end
$upscope $end
$enddefinitions $end
#0
$dumpvars
bx g
bx f
bx e
bx d
b0xxxxx c
bx b
bx a
bx `
bx _
b0 ^
b0 ]
bx \
bx [
bx Z
b1111111111 Y
b0 X
b0xxxxx W
b0 V
bx U
bx T
b0 S
bx R
bx Q
b0xxxxx P
bx O
bx N
bx M
bx L
bx K
zJ
b0xxxxx I
b0xxxxx H
bx G
bx F
bx E
bx D
bx C
1B
0A
bx @
x?
bx >
bx =
bx <
bx ;
x:
bx 9
bx 8
x7
16
bx 5
x4
bx 3
bx 2
b0 1
x0
x/
x.
bx -
b0 ,
bx +
bx *
b0xxxxx )
b0xxxxx (
bx '
x&
bx %
bx $
x#
0"
0!
$end
#10000
b0x 3
b0x C
b0x M
b0x d
1!
#20000
0!
#30000
1!
#40000
0!
#50000
1!
#60000
0!
#70000
b0 8
b0 K
b0 N
b0 Z
b0 g
1!
1"
#80000
0!
#90000
b0 +
b0 G
b0 _
16
b0 1
b0 S
b0 V
b0 ]
04
b10 $
b10 =
b10 Q
1&
0#
00
0.
0/
07
b10 %
b10 ;
b10 U
0?
b11 @
0:
b100000 <
b0 9
b110011 T
b1 D
b11 )
b11 H
b11 W
b11 c
b11 F
b10 (
b10 I
b10 P
b10 E
b1100010000000010110011 -
b1100010000000010110011 >
b1100010000000010110011 [
b0 \
b0x0 2
b0x0 O
b0x0 a
1!
#100000
0!
#110000
b101 +
b101 G
b101 _
06
b101 1
b101 S
b101 V
b101 ]
b11 '
b11 R
b11 e
b0 3
b0 C
b0 M
b0 d
1!
#120000
0!
#130000
b0 2
b0 O
b0 a
1!
#140000
0!
0"
#150000
b1 8
b1 K
b1 N
b1 Z
b1 g
1!
#160000
0!
#170000
b10 8
b10 K
b10 N
b10 Z
b10 g
bx +
bx G
bx _
b0xxxxx '
b0xxxxx R
b0xxxxx e
x6
bx 1
bx S
bx V
bx ]
x?
bx @
x:
b10xxxx <
bx 9
bx T
bx D
b0xxxxx )
b0xxxxx H
b0xxxxx W
b0xxxxx c
bx F
b0xxxxx (
b0xxxxx I
b0xxxxx P
bx E
bx -
bx >
bx [
b1 \
1!
#180000
0!
#190000
b11 8
b11 K
b11 N
b11 Z
b11 g
b0x 3
b0x C
b0x M
b0x d
b10 \
1!
#200000
0!
#210000
b0 8
b0 K
b0 N
b0 Z
b0 g
b11 \
b0x0000 2
b0x0000 O
b0x0000 a
1!
1"
#220000
0!
#230000
b101 +
b101 G
b101 _
06
b101 1
b101 S
b101 V
b101 ]
b11 '
b11 R
b11 e
0?
b11 @
0:
b100000 <
b0 9
b110011 T
b1 D
b11 )
b11 H
b11 W
b11 c
b11 F
b10 (
b10 I
b10 P
b10 E
b0x0 2
b0x0 O
b0x0 a
b1100010000000010110011 -
b1100010000000010110011 >
b1100010000000010110011 [
b0 \
1!
#240000
0!
#250000
b0 2
b0 O
b0 a
b0 3
b0 C
b0 M
b0 d
1!
#260000
0!
#270000
1!
#280000
0!
0"
#290000
b1 8
b1 K
b1 N
b1 Z
b1 g
1!
#300000
0!
#310000
b10 8
b10 K
b10 N
b10 Z
b10 g
bx +
bx G
bx _
b0xxxxx '
b0xxxxx R
b0xxxxx e
x6
bx 1
bx S
bx V
bx ]
x?
bx @
x:
b10xxxx <
bx 9
bx T
bx D
b0xxxxx )
b0xxxxx H
b0xxxxx W
b0xxxxx c
bx F
b0xxxxx (
b0xxxxx I
b0xxxxx P
bx E
bx -
bx >
bx [
b1 \
1!
#320000
0!
#330000
b11 8
b11 K
b11 N
b11 Z
b11 g
b10 \
b0x000 2
b0x000 O
b0x000 a
b0x 3
b0x C
b0x M
b0x d
1!
#340000
0!
#350000
b0 8
b0 K
b0 N
b0 Z
b0 g
b0x0000 2
b0x0000 O
b0x0000 a
b11 \
1!
1"
#360000
0!
#370000
b101 +
b101 G
b101 _
06
b101 1
b101 S
b101 V
b101 ]
b11 '
b11 R
b11 e
0?
b11 @
0:
b100000 <
b0 9
b110011 T
b1 D
b11 )
b11 H
b11 W
b11 c
b11 F
b10 (
b10 I
b10 P
b10 E
b1100010000000010110011 -
b1100010000000010110011 >
b1100010000000010110011 [
b0 \
b0x0 2
b0x0 O
b0x0 a
1!
#380000
0!
#390000
b0 3
b0 C
b0 M
b0 d
1!
#400000
0!
#410000
b0 2
b0 O
b0 a
1!
#420000
0!
0"
#430000
b1 8
b1 K
b1 N
b1 Z
b1 g
1!
#440000
0!
#450000
b10 8
b10 K
b10 N
b10 Z
b10 g
bx +
bx G
bx _
b0xxxxx '
b0xxxxx R
b0xxxxx e
x6
bx 1
bx S
bx V
bx ]
x?
bx @
x:
b10xxxx <
bx 9
bx T
bx D
b0xxxxx )
b0xxxxx H
b0xxxxx W
b0xxxxx c
bx F
b0xxxxx (
b0xxxxx I
b0xxxxx P
bx E
bx -
bx >
bx [
b1 \
1!
#460000
0!
#470000
b11 8
b11 K
b11 N
b11 Z
b11 g
b0x 3
b0x C
b0x M
b0x d
b10 \
1!
#480000
0!
#490000
b0 8
b0 K
b0 N
b0 Z
b0 g
b11 \
b0x0000 2
b0x0000 O
b0x0000 a
1!
1"
