ALU/alu.v
/* ALU Arithmetic and Logic Operations
----------------------------------------------------------------------
|opcode|   ALU Operation
----------------------------------------------------------------------
| 0000  |   resultado = a + b;
----------------------------------------------------------------------
| 0001  |   resultado = a - b;
----------------------------------------------------------------------
| 0010  |   resultado = a * b;
----------------------------------------------------------------------
| 0011  |   resultado = a / b;
----------------------------------------------------------------------
| 0100  |   resultado = a << 1;
----------------------------------------------------------------------
| 0101  |   resultado = a >> 1;
----------------------------------------------------------------------
| 0110  |   resultado = a rotated left by 1;
----------------------------------------------------------------------
| 0111  |   resultado = a rotated right by 1;
----------------------------------------------------------------------
| 1000  |   resultado = a and b;
----------------------------------------------------------------------
| 1001  |   resultado = a or b;
----------------------------------------------------------------------
| 1010  |   resultado = a xor b;
----------------------------------------------------------------------
| 1011  |   resultado = a nor b;
----------------------------------------------------------------------
| 1100  |   resultado = a nand b;
----------------------------------------------------------------------
| 1101  |   resultado = a xnor b;
----------------------------------------------------------------------
| 1110  |   resultado = 1 if a>b else 0;
----------------------------------------------------------------------
| 1111  |   resultado = 1 if a=b else 0;
----------------------------------------------------------------------*/

module alu(
           input [7:0] a,b,  // ALU 8-bit Inputs                 
           input [3:0] opcode,// ALU Selection
           output [7:0] resultado, // ALU 8-bit Output
           output zero // Carry Out Flag
    );
    reg [7:0] ALU_Result;
    wire [8:0] tmp;
    assign resultado = ALU_Result; // ALU out
    assign tmp = {1'b0,a} + {1'b0,b};
    assign zero = tmp[8]; // Carryout flag
    always @(*)
    begin
        case(opcode)
        4'b0000: // Addition
           ALU_Result = a + b ; 
        4'b0001: // Subtraction
           ALU_Result = a - b ;
        4'b0010: // Multiplication
           ALU_Result = a * b;
        4'b0011: // Division
           ALU_Result = a/b;
        4'b0100: // Logical shift left
           ALU_Result = a<<1;
         4'b0101: // Logical shift right
           ALU_Result = a>>1;
         4'b0110: // Rotate left
           ALU_Result = {a[6:0],a[7]};
         4'b0111: // Rotate right
           ALU_Result = {a[0],a[7:1]};
          4'b1000: //  Logical and 
           ALU_Result = a & b;
          4'b1001: //  Logical or
           ALU_Result = a | b;
          4'b1010: //  Logical xor 
           ALU_Result = a ^ b;
          4'b1011: //  Logical nor
           ALU_Result = ~(a | b);
          4'b1100: // Logical nand 
           ALU_Result = ~(a & b);
          4'b1101: // Logical xnor
           ALU_Result = ~(a ^ b);
          4'b1110: // Greater comparison
           ALU_Result = (a>b)?8'd1:8'd0 ;
          4'b1111: // Equal comparison   
            ALU_Result = (a==b)?8'd1:8'd0 ;
          default: ALU_Result = a + b ; 
        endcase
    end

endmodule

ALU/alu_tb.v
`timescale 1ns/1ns 
`include "alu.v"

module tb_alu;

 reg[7:0] a,b;
 reg[3:0] opcode;
 wire[7:0] resultado;
 wire zero;
 
 integer i;

 alu test_unit(a,b,opcode,resultado,zero );

initial begin
    $dumpfile("alu_tb.vcd");
	$dumpvars;
    
    a = 8'h0A;
    b = 8'h02;
    opcode = 4'h0;
      
    for (i=0;i<=15;i=i+1)
    begin
    opcode = opcode + 8'h01;
     #10;
    end;
      
    a = 8'hF6;
    b = 8'h0A;
      
    end
endmodule

ALU/alu_tb.vcd
$date
	Thu Dec 03 01:36:37 2020
$end
$version
	Icarus Verilog
$end
$timescale
	1ns
$end
$scope module tb_alu $end
$var wire 1 ! zero $end
$var wire 8 " resultado [7:0] $end
$var reg 8 # a [7:0] $end
$var reg 8 $ b [7:0] $end
$var reg 4 % opcode [3:0] $end
$var integer 32 & i [31:0] $end
$scope module test_unit $end
$var wire 8 ' a [7:0] $end
$var wire 8 ( b [7:0] $end
$var wire 4 ) opcode [3:0] $end
$var wire 8 * resultado [7:0] $end
$var wire 1 ! zero $end
$var wire 9 + tmp [8:0] $end
$var reg 8 , ALU_Result [7:0] $end
$upscope $end
$upscope $end
$enddefinitions $end
#0
$dumpvars
b1000 ,
b1100 +
b1000 *
b1 )
b10 (
b1010 '
b0 &
b1 %
b10 $
b1010 #
b1000 "
0!
$end
#10
b10100 "
b10100 *
b10100 ,
b10 %
b10 )
b1 &
#20
b101 "
b101 *
b101 ,
b11 %
b11 )
b10 &
#30
b10100 "
b10100 *
b10100 ,
b100 %
b100 )
b11 &
#40
b101 "
b101 *
b101 ,
b101 %
b101 )
b100 &
#50
b10100 "
b10100 *
b10100 ,
b110 %
b110 )
b101 &
#60
b101 "
b101 *
b101 ,
b111 %
b111 )
b110 &
#70
b10 "
b10 *
b10 ,
b1000 %
b1000 )
b111 &
#80
b1010 "
b1010 *
b1010 ,
b1001 %
b1001 )
b1000 &
#90
1!
b11111110 "
b11111110 *
b11111110 ,
b1010 $
b1010 (
b100000000 +
b11110110 #
b11110110 '
b1001 &
